tigris_boto3_ext/__init__.py
tigris_boto3_ext/_internal.py
tigris_boto3_ext/context_managers.py
tigris_boto3_ext/decorators.py
tigris_boto3_ext/helpers.py
tigris_boto3_ext/py.typed
tigris_boto3_ext-0.1.1.dist-info/licenses/LICENSE
tigris_boto3_ext-0.1.1.dist-info/METADATA
tigris_boto3_ext-0.1.1.dist-info/WHEEL
tigris_boto3_ext-0.1.1.dist-info/top_level.txt
tigris_boto3_ext-0.1.1.dist-info/RECORD
