Metadata-Version: 2.4
Name: tigris-boto3-ext
Version: 0.1.1
Summary: Extend boto3 with Tigris-specific features like snapshots and bucket forking
Author-email: Tigris Data <support@tigrisdata.com>
License-Expression: Apache-2.0
Project-URL: Homepage, https://github.com/tigrisdata/tigris-boto3-ext
Project-URL: Documentation, https://github.com/tigrisdata/tigris-boto3-ext#readme
Project-URL: Repository, https://github.com/tigrisdata/tigris-boto3-ext
Project-URL: Issues, https://github.com/tigrisdata/tigris-boto3-ext/issues
Keywords: tigris,boto3,s3,object-storage,snapshot,fork
Classifier: Development Status :: 3 - Alpha
Classifier: Intended Audience :: Developers
Classifier: Programming Language :: Python :: 3
Classifier: Programming Language :: Python :: 3.9
Classifier: Programming Language :: Python :: 3.10
Classifier: Programming Language :: Python :: 3.11
Classifier: Programming Language :: Python :: 3.12
Classifier: Topic :: Software Development :: Libraries :: Python Modules
Requires-Python: >=3.9
License-File: LICENSE
Requires-Dist: boto3>=1.26.0
Provides-Extra: dev
Requires-Dist: pytest>=7.0.0; extra == "dev"
Requires-Dist: pytest-cov>=4.0.0; extra == "dev"
Requires-Dist: mypy>=1.0.0; extra == "dev"
Requires-Dist: black>=23.0.0; extra == "dev"
Requires-Dist: ruff>=0.1.0; extra == "dev"
Requires-Dist: boto3-stubs[s3]>=1.26.0; extra == "dev"
Requires-Dist: twine>=4.0.0; extra == "dev"
Requires-Dist: build>=1.0.0; extra == "dev"
Dynamic: license-file
